{
    "homepage": "https://bitsum.com/",
    "description": "Real-Time CPU Optimization and Automation",
    "version": "14.1.0",
    "license": "Freemium",
    "url": "https://dl.bitsum.com/files/processlassosetup64.exe#/dl.7z",
    "hash": "fb00ea98cb78dcb72e3c95a3665281e213527f54a91ff485969a43be9651577e",
    "extract_to": "Process Lasso",
    "shortcuts": [
        [
            "Process Lasso/ProcessLassoLauncher.exe",
            "Process Lasso"
        ]
    ],
    "persist": [
        "Process Lasso/config",
        "Process Lasso/logs"
    ],
    "installer": {
        "script": "Remove-Item \"$dir/Process Lasso/`$PLUGINSDIR\" -Recurse"
    },
    "checkver": {
        "url": "https://bitsum.com/changes/processlasso/",
        "regex": "Process Lasso v.*>([\\d.]+)"
    },
    "autoupdate": {
        "url": "https://dl.bitsum.com/files/processlassosetup64.exe#/dl.7z"
    }
}
